nti.sphinxcontrib_programoutput-0.9-py2.7-nspkg.pth
nti.sphinxcontrib_programoutput-0.9.dist-info/DESCRIPTION.rst
nti.sphinxcontrib_programoutput-0.9.dist-info/METADATA
nti.sphinxcontrib_programoutput-0.9.dist-info/RECORD
nti.sphinxcontrib_programoutput-0.9.dist-info/WHEEL
nti.sphinxcontrib_programoutput-0.9.dist-info/metadata.json
nti.sphinxcontrib_programoutput-0.9.dist-info/namespace_packages.txt
nti.sphinxcontrib_programoutput-0.9.dist-info/top_level.txt
sphinxcontrib/programoutput/__init__.py
sphinxcontrib/programoutput/tests/__init__.py
sphinxcontrib/programoutput/tests/test_cache.py
sphinxcontrib/programoutput/tests/test_command.py
sphinxcontrib/programoutput/tests/test_directive.py
sphinxcontrib/programoutput/tests/test_setup.py
sphinxcontrib/programoutput/tests/test_util.py
