Metadata-Version: 2.0
Name: nti.sphinxcontrib-programoutput
Version: 0.9
Summary: Sphinx extension to include program output
Home-page: https://sphinxcontrib-programoutput.readthedocs.org/
Author: Sebastian Wiesner
Author-email: lunaryorn@gmail.com
License: BSD
Download-URL: https://pypi.python.org/pypi/sphinxcontrib-programoutput
Platform: any
Classifier: Development Status :: 5 - Production/Stable
Classifier: Intended Audience :: Developers
Classifier: License :: OSI Approved :: BSD License
Classifier: Operating System :: OS Independent
Classifier: Programming Language :: Python
Classifier: Programming Language :: Python :: 2
Classifier: Programming Language :: Python :: 3
Classifier: Programming Language :: Python :: 2.7
Classifier: Programming Language :: Python :: 3.5
Classifier: Programming Language :: Python :: 3.6
Classifier: Programming Language :: Python :: Implementation :: CPython
Classifier: Programming Language :: Python :: Implementation :: PyPy
Classifier: Topic :: Documentation
Classifier: Topic :: Utilities
Requires-Dist: Sphinx (>=1.3.5)
Provides-Extra: test
